ds_flow/__init__.py
ds_flow/general_utils.py
ds_flow/io_flow/__init__.py
ds_flow/io_flow/io_utils.py
ds_flow/np_flow/__init__.py
ds_flow/np_flow/math_flow.py
ds_flow/np_flow/np_imaging.py
ds_flow/np_flow/numpy_utils.py
ds_flow/pandas_flow/__init__.py
ds_flow/sk_flow/__init__.py
ds_flow/sk_flow/modeling.py
ds_flow/torch_flow/__init__.py
ds_flow/torch_flow/data_loaders.py
ds_flow/torch_flow/datasets.py
ds_flow/torch_flow/evaluation.py
ds_flow/torch_flow/models.py
ds_flow/torch_flow/sample_training.py
ds_flow/torch_flow/torch_utils.py
ds_flow/torch_flow/training.py
ds_flow/torch_flow/transforms.py
dsflow_py-0.0.5.dist-info/LICENSE.md
dsflow_py-0.0.5.dist-info/METADATA
dsflow_py-0.0.5.dist-info/WHEEL
dsflow_py-0.0.5.dist-info/RECORD
